lib/__init__.py
lib/ddeclient.py
rakuten_rss-0.0.5.dist-info/LICENSE
rakuten_rss-0.0.5.dist-info/METADATA
rakuten_rss-0.0.5.dist-info/WHEEL
rakuten_rss-0.0.5.dist-info/top_level.txt
rakuten_rss-0.0.5.dist-info/RECORD
