Metadata-Version: 2.1
Name: rakuten-rss
Version: 0.0.5
Summary: Python module for Rakuten RSS
Home-page: https://github.com/zaq9/rakuten_rss
Author: zaq
Author-email: zaq_9@yahoo.co.jp
License: MIT
